treech/ClassificationTree.py
treech/__init__.py
treech-0.4.0.dist-info/LICENSE.txt
treech-0.4.0.dist-info/METADATA
treech-0.4.0.dist-info/WHEEL
treech-0.4.0.dist-info/top_level.txt
treech-0.4.0.dist-info/RECORD
