Metadata-Version: 2.1
Name: treech
Version: 0.4.0
Summary: with this package you can create data-based decision trees manually, semi-automatically, or automatically
Home-page: https://github.com/dein_github/my_library
Author: Yannik Fleischer
Author-email: yanflei@math.uni-paderborn.de
Classifier: Programming Language :: Python :: 3
Classifier: License :: OSI Approved :: MIT License
Classifier: Operating System :: OS Independent
Requires-Python: >=3.6
License-File: LICENSE.txt
Requires-Dist: numpy==1.26.4
Requires-Dist: pandas==2.2.2
Requires-Dist: graphviz==0.20.1
